lying/__init__.py
lying/__main__.py
lying/cli.py
lying/terminal.py
lying/render/__init__.py
lying/render/basic.py
lying/render/common.py
lying/render/mixin.py
lying/utils/__init__.py
lying/utils/dispatch.py
lying/utils/instruction.py
lying/utils/misc.py
lying/utils/settings.py
lying-0.1.1.dist-info/LICENSE
lying-0.1.1.dist-info/METADATA
lying-0.1.1.dist-info/WHEEL
lying-0.1.1.dist-info/entry_points.txt
lying-0.1.1.dist-info/top_level.txt
lying-0.1.1.dist-info/RECORD
