Metadata-Version: 2.1
Name: lying
Version: 0.1.1
Summary: run a fake terminal
Home-page: https://github.com/axju/lying
Author: axju
Author-email: axel.juraske@short-report.de
License: MIT
Platform: UNKNOWN
Classifier: Intended Audience :: Developers
Classifier: Operating System :: OS Independent
Classifier: Programming Language :: Python
Classifier: Programming Language :: Python :: 3.6
Classifier: Programming Language :: Python :: 3.7
Classifier: Programming Language :: Python :: 3.8
